{
  "id": "posthog-ios",
  "hogRef": "0.3",
  "info": {
    "version": "3.34.0",
    "id": "posthog-ios",
    "title": "PostHog iOS SDK",
    "description": "PostHog iOS SDK allows you to automatically capture usage and send events to PostHog from iOS applications.",
    "slugPrefix": "posthog-ios",
    "specUrl": "https://github.com/PostHog/posthog-ios"
  },
  "classes": [
    {
      "description": "The PostHogSDK class",
      "id": "PostHogSDK",
      "title": "PostHogSDK",
      "functions": [
        {
          "category": "Identification",
          "description": "alias method",
          "details": "Detailed description of alias",
          "id": "alias",
          "showDocs": true,
          "title": "alias",
          "examples": [
            {
              "id": "basic_alias",
              "name": "Basic alias",
              "code": "PostHogSDK.shared.alias(\"alias_value\")"
            }
          ],
          "releaseTag": "public",
          "params": [
            {
              "name": "alias",
              "type": "String",
              "isOptional": false
            }
          ],
          "returnType": {
            "id": "Void",
            "name": "Void"
          },
          "path": "PostHog/PostHogSDK.swift"
        },
        {
          "category": "Capture",
          "description": "capture method",
          "details": "Detailed description of capture",
          "id": "capture",
          "showDocs": true,
          "title": "capture",
          "examples": [
            {
              "id": "basic_capture",
              "name": "Basic capture",
              "code": "PostHogSDK.shared.capture(\"button_clicked\")"
            }
          ],
          "releaseTag": "public",
          "params": [
            {
              "name": "event",
              "type": "String",
              "isOptional": false
            }
          ],
          "returnType": {
            "id": "Void",
            "name": "Void"
          },
          "path": "PostHog/PostHogSDK.swift"
        },
        {
          "category": "Capture",
          "description": "capture method",
          "details": "Detailed description of capture",
          "id": "capture",
          "showDocs": true,
          "title": "capture",
          "examples": [
            {
              "id": "basic_capture",
              "name": "Basic capture",
              "code": "PostHogSDK.shared.capture(\"__value\", distinctId: \"user_123\", properties: \"properties_value\", userProperties: \"userProperties_value\", userPropertiesSetOnce: \"userPropertiesSetOnce_value\", groups: \"groups_value\", param6: \"param6_value\")"
            }
          ],
          "releaseTag": "public",
          "params": [
            {
              "name": "_",
              "type": "String",
              "isOptional": false
            },
            {
              "name": "distinctId",
              "type": "String",
              "isOptional": false
            },
            {
              "name": "properties",
              "type": "String",
              "isOptional": false
            },
            {
              "name": "userProperties",
              "type": "String",
              "isOptional": false
            },
            {
              "name": "userPropertiesSetOnce",
              "type": "String",
              "isOptional": false
            },
            {
              "name": "groups",
              "type": "String",
              "isOptional": false
            },
            {
              "name": "param6",
              "type": "String",
              "isOptional": false
            }
          ],
          "returnType": {
            "id": "Void",
            "name": "Void"
          },
          "path": "PostHog/PostHogSDK.swift"
        },
        {
          "category": "Capture",
          "description": "capture method",
          "details": "Detailed description of capture",
          "id": "capture",
          "showDocs": true,
          "title": "capture",
          "examples": [
            {
              "id": "basic_capture",
              "name": "Basic capture",
              "code": "PostHogSDK.shared.capture(\"__value\", distinctId: \"user_123\", properties: \"properties_value\", userProperties: \"userProperties_value\", userPropertiesSetOnce: \"userPropertiesSetOnce_value\", groups: \"groups_value\", timestamp: \"timestamp_value\", param7: param7)"
            }
          ],
          "releaseTag": "public",
          "params": [
            {
              "name": "_",
              "type": "String",
              "isOptional": false
            },
            {
              "name": "distinctId",
              "type": "String",
              "isOptional": false
            },
            {
              "name": "properties",
              "type": "String",
              "isOptional": false
            },
            {
              "name": "userProperties",
              "type": "String",
              "isOptional": false
            },
            {
              "name": "userPropertiesSetOnce",
              "type": "String",
              "isOptional": false
            },
            {
              "name": "groups",
              "type": "String",
              "isOptional": false
            },
            {
              "name": "timestamp",
              "type": "String",
              "isOptional": false
            },
            {
              "name": "param7",
              "type": "Date",
              "isOptional": false
            }
          ],
          "returnType": {
            "id": "Void",
            "name": "Void"
          },
          "path": "PostHog/PostHogSDK.swift"
        },
        {
          "category": "Capture",
          "description": "capture method",
          "details": "Detailed description of capture",
          "id": "capture",
          "showDocs": true,
          "title": "capture",
          "examples": [
            {
              "id": "basic_capture",
              "name": "Basic capture",
              "code": "PostHogSDK.shared.capture(\"__value\", properties: \"properties_value\")"
            }
          ],
          "releaseTag": "public",
          "params": [
            {
              "name": "_",
              "type": "String",
              "isOptional": false
            },
            {
              "name": "properties",
              "type": "String",
              "isOptional": false
            }
          ],
          "returnType": {
            "id": "Void",
            "name": "Void"
          },
          "path": "PostHog/PostHogSDK.swift"
        },
        {
          "category": "Capture",
          "description": "capture method",
          "details": "Detailed description of capture",
          "id": "capture",
          "showDocs": true,
          "title": "capture",
          "examples": [
            {
              "id": "basic_capture",
              "name": "Basic capture",
              "code": "PostHogSDK.shared.capture(\"__value\", properties: \"properties_value\", userProperties: \"userProperties_value\")"
            }
          ],
          "releaseTag": "public",
          "params": [
            {
              "name": "_",
              "type": "String",
              "isOptional": false
            },
            {
              "name": "properties",
              "type": "String",
              "isOptional": false
            },
            {
              "name": "userProperties",
              "type": "String",
              "isOptional": false
            }
          ],
          "returnType": {
            "id": "Void",
            "name": "Void"
          },
          "path": "PostHog/PostHogSDK.swift"
        },
        {
          "category": "Capture",
          "description": "capture method",
          "details": "Detailed description of capture",
          "id": "capture",
          "showDocs": true,
          "title": "capture",
          "examples": [
            {
              "id": "basic_capture",
              "name": "Basic capture",
              "code": "PostHogSDK.shared.capture(\"__value\", properties: \"properties_value\", userProperties: \"userProperties_value\", userPropertiesSetOnce: \"userPropertiesSetOnce_value\")"
            }
          ],
          "releaseTag": "public",
          "params": [
            {
              "name": "_",
              "type": "String",
              "isOptional": false
            },
            {
              "name": "properties",
              "type": "String",
              "isOptional": false
            },
            {
              "name": "userProperties",
              "type": "String",
              "isOptional": false
            },
            {
              "name": "userPropertiesSetOnce",
              "type": "String",
              "isOptional": false
            }
          ],
          "returnType": {
            "id": "Void",
            "name": "Void"
          },
          "path": "PostHog/PostHogSDK.swift"
        },
        {
          "category": "Capture",
          "description": "capture method",
          "details": "Detailed description of capture",
          "id": "capture",
          "showDocs": true,
          "title": "capture",
          "examples": [
            {
              "id": "basic_capture",
              "name": "Basic capture",
              "code": "PostHogSDK.shared.capture(\"__value\", properties: \"properties_value\", userProperties: \"userProperties_value\", userPropertiesSetOnce: \"userPropertiesSetOnce_value\", groups: \"groups_value\", param5: \"param5_value\")"
            }
          ],
          "releaseTag": "public",
          "params": [
            {
              "name": "_",
              "type": "String",
              "isOptional": false
            },
            {
              "name": "properties",
              "type": "String",
              "isOptional": false
            },
            {
              "name": "userProperties",
              "type": "String",
              "isOptional": false
            },
            {
              "name": "userPropertiesSetOnce",
              "type": "String",
              "isOptional": false
            },
            {
              "name": "groups",
              "type": "String",
              "isOptional": false
            },
            {
              "name": "param5",
              "type": "String",
              "isOptional": false
            }
          ],
          "returnType": {
            "id": "Void",
            "name": "Void"
          },
          "path": "PostHog/PostHogSDK.swift"
        },
        {
          "category": "Configuration",
          "description": "close method",
          "details": "Detailed description of close",
          "id": "close",
          "showDocs": true,
          "title": "close",
          "examples": [
            {
              "id": "basic_close",
              "name": "Basic close",
              "code": "PostHogSDK.shared.close()"
            }
          ],
          "releaseTag": "public",
          "params": [],
          "returnType": {
            "id": "Void",
            "name": "Void"
          },
          "path": "PostHog/PostHogSDK.swift"
        },
        {
          "category": "Configuration",
          "description": "debug method",
          "details": "Detailed description of debug",
          "id": "debug",
          "showDocs": true,
          "title": "debug",
          "examples": [
            {
              "id": "basic_debug",
              "name": "Basic debug",
              "code": "PostHogSDK.shared.debug(true)"
            }
          ],
          "releaseTag": "public",
          "params": [
            {
              "name": "value",
              "type": "Bool",
              "isOptional": false
            }
          ],
          "returnType": {
            "id": "Void",
            "name": "Void"
          },
          "path": "PostHog/PostHogSDK.swift"
        },
        {
          "category": "Session replay",
          "description": "endSession method",
          "details": "Detailed description of endSession",
          "id": "endSession",
          "showDocs": true,
          "title": "endSession",
          "examples": [
            {
              "id": "basic_endSession",
              "name": "Basic endSession",
              "code": "PostHogSDK.shared.endSession()"
            }
          ],
          "releaseTag": "public",
          "params": [],
          "returnType": {
            "id": "Void",
            "name": "Void"
          },
          "path": "PostHog/PostHogSDK.swift"
        },
        {
          "category": "Configuration",
          "description": "flush method",
          "details": "Detailed description of flush",
          "id": "flush",
          "showDocs": true,
          "title": "flush",
          "examples": [
            {
              "id": "basic_flush",
              "name": "Basic flush",
              "code": "PostHogSDK.shared.flush()"
            }
          ],
          "releaseTag": "public",
          "params": [],
          "returnType": {
            "id": "Void",
            "name": "Void"
          },
          "path": "PostHog/PostHogSDK.swift"
        },
        {
          "category": "Identification",
          "description": "getAnonymousId method",
          "details": "Detailed description of getAnonymousId",
          "id": "getAnonymousId",
          "showDocs": true,
          "title": "getAnonymousId",
          "examples": [
            {
              "id": "basic_getAnonymousId",
              "name": "Basic getAnonymousId",
              "code": "PostHogSDK.shared.getAnonymousId()"
            }
          ],
          "releaseTag": "public",
          "params": [],
          "returnType": {
            "id": "Void",
            "name": "Void"
          },
          "path": "PostHog/PostHogSDK.swift"
        },
        {
          "category": "Identification",
          "description": "getDistinctId method",
          "details": "Detailed description of getDistinctId",
          "id": "getDistinctId",
          "showDocs": true,
          "title": "getDistinctId",
          "examples": [
            {
              "id": "basic_getDistinctId",
              "name": "Basic getDistinctId",
              "code": "PostHogSDK.shared.getDistinctId()"
            }
          ],
          "releaseTag": "public",
          "params": [],
          "returnType": {
            "id": "Void",
            "name": "Void"
          },
          "path": "PostHog/PostHogSDK.swift"
        },
        {
          "category": "Feature flags",
          "description": "getFeatureFlag method",
          "details": "Detailed description of getFeatureFlag",
          "id": "getFeatureFlag",
          "showDocs": true,
          "title": "getFeatureFlag",
          "examples": [
            {
              "id": "basic_getFeatureFlag",
              "name": "Basic getFeatureFlag",
              "code": "PostHogSDK.shared.getFeatureFlag(\"value_value\")"
            }
          ],
          "releaseTag": "public",
          "params": [
            {
              "name": "value",
              "type": "String",
              "isOptional": false
            }
          ],
          "returnType": {
            "id": "Void",
            "name": "Void"
          },
          "path": "PostHog/PostHogSDK.swift"
        },
        {
          "category": "Feature flags",
          "description": "getFeatureFlagPayload method",
          "details": "Detailed description of getFeatureFlagPayload",
          "id": "getFeatureFlagPayload",
          "showDocs": true,
          "title": "getFeatureFlagPayload",
          "examples": [
            {
              "id": "basic_getFeatureFlagPayload",
              "name": "Basic getFeatureFlagPayload",
              "code": "PostHogSDK.shared.getFeatureFlagPayload(\"value_value\")"
            }
          ],
          "releaseTag": "public",
          "params": [
            {
              "name": "value",
              "type": "String",
              "isOptional": false
            }
          ],
          "returnType": {
            "id": "Void",
            "name": "Void"
          },
          "path": "PostHog/PostHogSDK.swift"
        },
        {
          "category": "Session replay",
          "description": "getSessionId method",
          "details": "Detailed description of getSessionId",
          "id": "getSessionId",
          "showDocs": true,
          "title": "getSessionId",
          "examples": [
            {
              "id": "basic_getSessionId",
              "name": "Basic getSessionId",
              "code": "PostHogSDK.shared.getSessionId()"
            }
          ],
          "releaseTag": "public",
          "params": [],
          "returnType": {
            "id": "Void",
            "name": "Void"
          },
          "path": "PostHog/PostHogSDK.swift"
        },
        {
          "category": "Configuration",
          "description": "group method",
          "details": "Detailed description of group",
          "id": "group",
          "showDocs": true,
          "title": "group",
          "examples": [
            {
              "id": "basic_group",
              "name": "Basic group",
              "code": "PostHogSDK.shared.group(\"type_value\", key: \"group_feature\")"
            }
          ],
          "releaseTag": "public",
          "params": [
            {
              "name": "type",
              "type": "String",
              "isOptional": false
            },
            {
              "name": "key",
              "type": "String",
              "isOptional": false
            }
          ],
          "returnType": {
            "id": "Void",
            "name": "Void"
          },
          "path": "PostHog/PostHogSDK.swift"
        },
        {
          "category": "Configuration",
          "description": "group method",
          "details": "Detailed description of group",
          "id": "group",
          "showDocs": true,
          "title": "group",
          "examples": [
            {
              "id": "basic_group",
              "name": "Basic group",
              "code": "PostHogSDK.shared.group(\"type_value\", key: \"group_feature\", groupProperties: \"groupProperties_value\")"
            }
          ],
          "releaseTag": "public",
          "params": [
            {
              "name": "type",
              "type": "String",
              "isOptional": false
            },
            {
              "name": "key",
              "type": "String",
              "isOptional": false
            },
            {
              "name": "groupProperties",
              "type": "String",
              "isOptional": false
            }
          ],
          "returnType": {
            "id": "Void",
            "name": "Void"
          },
          "path": "PostHog/PostHogSDK.swift"
        },
        {
          "category": "Identification",
          "description": "identify method",
          "details": "Detailed description of identify",
          "id": "identify",
          "showDocs": true,
          "title": "identify",
          "examples": [
            {
              "id": "basic_identify",
              "name": "Basic identify",
              "code": "PostHogSDK.shared.identify(\"user_123\")"
            }
          ],
          "releaseTag": "public",
          "params": [
            {
              "name": "distinctId",
              "type": "String",
              "isOptional": false
            }
          ],
          "returnType": {
            "id": "Void",
            "name": "Void"
          },
          "path": "PostHog/PostHogSDK.swift"
        },
        {
          "category": "Identification",
          "description": "identify method",
          "details": "Detailed description of identify",
          "id": "identify",
          "showDocs": true,
          "title": "identify",
          "examples": [
            {
              "id": "basic_identify",
              "name": "Basic identify",
              "code": "PostHogSDK.shared.identify(\"__value\", userProperties: \"userProperties_value\")"
            }
          ],
          "releaseTag": "public",
          "params": [
            {
              "name": "_",
              "type": "String",
              "isOptional": false
            },
            {
              "name": "userProperties",
              "type": "String",
              "isOptional": false
            }
          ],
          "returnType": {
            "id": "Void",
            "name": "Void"
          },
          "path": "PostHog/PostHogSDK.swift"
        },
        {
          "category": "Identification",
          "description": "identify method",
          "details": "Detailed description of identify",
          "id": "identify",
          "showDocs": true,
          "title": "identify",
          "examples": [
            {
              "id": "basic_identify",
              "name": "Basic identify",
              "code": "PostHogSDK.shared.identify(\"__value\", userProperties: \"userProperties_value\", userPropertiesSetOnce: \"userPropertiesSetOnce_value\")"
            }
          ],
          "releaseTag": "public",
          "params": [
            {
              "name": "_",
              "type": "String",
              "isOptional": false
            },
            {
              "name": "userProperties",
              "type": "String",
              "isOptional": false
            },
            {
              "name": "userPropertiesSetOnce",
              "type": "String",
              "isOptional": false
            }
          ],
          "returnType": {
            "id": "Void",
            "name": "Void"
          },
          "path": "PostHog/PostHogSDK.swift"
        },
        {
          "category": "Feature flags",
          "description": "isFeatureEnabled method",
          "details": "Detailed description of isFeatureEnabled",
          "id": "isFeatureEnabled",
          "showDocs": true,
          "title": "isFeatureEnabled",
          "examples": [
            {
              "id": "basic_isFeatureEnabled",
              "name": "Basic isFeatureEnabled",
              "code": "PostHogSDK.shared.isFeatureEnabled(\"value_value\", value: true)"
            }
          ],
          "releaseTag": "public",
          "params": [
            {
              "name": "value",
              "type": "String",
              "isOptional": false
            },
            {
              "name": "value",
              "type": "Bool",
              "isOptional": false
            }
          ],
          "returnType": {
            "id": "Void",
            "name": "Void"
          },
          "path": "PostHog/PostHogSDK.swift"
        },
        {
          "category": "Privacy",
          "description": "isOptOut method",
          "details": "Detailed description of isOptOut",
          "id": "isOptOut",
          "showDocs": true,
          "title": "isOptOut",
          "examples": [
            {
              "id": "basic_isOptOut",
              "name": "Basic isOptOut",
              "code": "PostHogSDK.shared.isOptOut()"
            }
          ],
          "releaseTag": "public",
          "params": [],
          "returnType": {
            "id": "Void",
            "name": "Void"
          },
          "path": "PostHog/PostHogSDK.swift"
        },
        {
          "category": "Privacy",
          "description": "optIn method",
          "details": "Detailed description of optIn",
          "id": "optIn",
          "showDocs": true,
          "title": "optIn",
          "examples": [
            {
              "id": "basic_optIn",
              "name": "Basic optIn",
              "code": "PostHogSDK.shared.optIn()"
            }
          ],
          "releaseTag": "public",
          "params": [],
          "returnType": {
            "id": "Void",
            "name": "Void"
          },
          "path": "PostHog/PostHogSDK.swift"
        },
        {
          "category": "Privacy",
          "description": "optOut method",
          "details": "Detailed description of optOut",
          "id": "optOut",
          "showDocs": true,
          "title": "optOut",
          "examples": [
            {
              "id": "basic_optOut",
              "name": "Basic optOut",
              "code": "PostHogSDK.shared.optOut()"
            }
          ],
          "releaseTag": "public",
          "params": [],
          "returnType": {
            "id": "Void",
            "name": "Void"
          },
          "path": "PostHog/PostHogSDK.swift"
        },
        {
          "category": "Configuration",
          "description": "register method",
          "details": "Detailed description of register",
          "id": "register",
          "showDocs": true,
          "title": "register",
          "examples": [
            {
              "id": "basic_register",
              "name": "Basic register",
              "code": "PostHogSDK.shared.register()"
            }
          ],
          "releaseTag": "public",
          "params": [],
          "returnType": {
            "id": "Void",
            "name": "Void"
          },
          "path": "PostHog/PostHogSDK.swift"
        },
        {
          "category": "Feature flags",
          "description": "reloadFeatureFlags method",
          "details": "Detailed description of reloadFeatureFlags",
          "id": "reloadFeatureFlags",
          "showDocs": true,
          "title": "reloadFeatureFlags",
          "examples": [
            {
              "id": "basic_reloadFeatureFlags",
              "name": "Basic reloadFeatureFlags",
              "code": "PostHogSDK.shared.reloadFeatureFlags()"
            }
          ],
          "releaseTag": "public",
          "params": [],
          "returnType": {
            "id": "Void",
            "name": "Void"
          },
          "path": "PostHog/PostHogSDK.swift"
        },
        {
          "category": "Feature flags",
          "description": "reloadFeatureFlags method",
          "details": "Detailed description of reloadFeatureFlags",
          "id": "reloadFeatureFlags",
          "showDocs": true,
          "title": "reloadFeatureFlags",
          "examples": [
            {
              "id": "basic_reloadFeatureFlags",
              "name": "Basic reloadFeatureFlags",
              "code": "PostHogSDK.shared.reloadFeatureFlags()"
            }
          ],
          "releaseTag": "public",
          "params": [],
          "returnType": {
            "id": "Void",
            "name": "Void"
          },
          "path": "PostHog/PostHogSDK.swift"
        },
        {
          "category": "Privacy",
          "description": "reset method",
          "details": "Detailed description of reset",
          "id": "reset",
          "showDocs": true,
          "title": "reset",
          "examples": [
            {
              "id": "basic_reset",
              "name": "Basic reset",
              "code": "PostHogSDK.shared.reset()"
            }
          ],
          "releaseTag": "public",
          "params": [],
          "returnType": {
            "id": "Void",
            "name": "Void"
          },
          "path": "PostHog/PostHogSDK.swift"
        },
        {
          "category": "Feature flags",
          "description": "Clears all group properties for feature flag evaluation.",
          "details": "Clears all group properties for feature flag evaluation.",
          "id": "resetGroupPropertiesForFlags",
          "showDocs": true,
          "title": "resetGroupPropertiesForFlags",
          "examples": [
            {
              "id": "basic_resetGroupPropertiesForFlags",
              "name": "Basic resetGroupPropertiesForFlags",
              "code": "PostHogSDK.shared.resetGroupPropertiesForFlags()"
            }
          ],
          "releaseTag": "public",
          "params": [],
          "returnType": {
            "id": "Void",
            "name": "Void"
          },
          "path": "PostHog/PostHogSDK.swift"
        },
        {
          "category": "Feature flags",
          "description": "Clears group properties for feature flag evaluation for a specific group type.",
          "details": "Clears group properties for feature flag evaluation for a specific group type.",
          "id": "resetGroupPropertiesForFlags",
          "showDocs": true,
          "title": "resetGroupPropertiesForFlags",
          "examples": [
            {
              "id": "basic_resetGroupPropertiesForFlags",
              "name": "Basic resetGroupPropertiesForFlags",
              "code": "PostHogSDK.shared.resetGroupPropertiesForFlags(\"type_value\")"
            }
          ],
          "releaseTag": "public",
          "params": [
            {
              "name": "type",
              "type": "String",
              "isOptional": false
            }
          ],
          "returnType": {
            "id": "Void",
            "name": "Void"
          },
          "path": "PostHog/PostHogSDK.swift"
        },
        {
          "category": "Feature flags",
          "description": "Resets all person properties that were set for feature flag evaluation.",
          "details": "Resets all person properties that were set for feature flag evaluation.",
          "id": "resetPersonPropertiesForFlags",
          "showDocs": true,
          "title": "resetPersonPropertiesForFlags",
          "examples": [
            {
              "id": "basic_resetPersonPropertiesForFlags",
              "name": "Basic resetPersonPropertiesForFlags",
              "code": "PostHogSDK.shared.resetPersonPropertiesForFlags()"
            }
          ],
          "releaseTag": "public",
          "params": [],
          "returnType": {
            "id": "Void",
            "name": "Void"
          },
          "path": "PostHog/PostHogSDK.swift"
        },
        {
          "category": "Capture",
          "description": "screen method",
          "details": "Detailed description of screen",
          "id": "screen",
          "showDocs": true,
          "title": "screen",
          "examples": [
            {
              "id": "basic_screen",
              "name": "Basic screen",
              "code": "PostHogSDK.shared.screen(\"name_value\")"
            }
          ],
          "releaseTag": "public",
          "params": [
            {
              "name": "name",
              "type": "String",
              "isOptional": false
            }
          ],
          "returnType": {
            "id": "Void",
            "name": "Void"
          },
          "path": "PostHog/PostHogSDK.swift"
        },
        {
          "category": "Capture",
          "description": "screen method",
          "details": "Detailed description of screen",
          "id": "screen",
          "showDocs": true,
          "title": "screen",
          "examples": [
            {
              "id": "basic_screen",
              "name": "Basic screen",
              "code": "PostHogSDK.shared.screen(\"__value\", properties: \"properties_value\")"
            }
          ],
          "releaseTag": "public",
          "params": [
            {
              "name": "_",
              "type": "String",
              "isOptional": false
            },
            {
              "name": "properties",
              "type": "String",
              "isOptional": false
            }
          ],
          "returnType": {
            "id": "Void",
            "name": "Void"
          },
          "path": "PostHog/PostHogSDK.swift"
        },
        {
          "category": "Feature flags",
          "description": "Sets properties for a specific group type to include when evaluating feature flags.   These properties supplement the standard group information sent to PostHog for flag evaluation,   providing additional context that can be used in flag targeting conditions.",
          "details": "Sets properties for a specific group type to include when evaluating feature flags.   These properties supplement the standard group information sent to PostHog for flag evaluation,   providing additional context that can be used in flag targeting conditions.",
          "id": "setGroupPropertiesForFlags",
          "showDocs": true,
          "title": "setGroupPropertiesForFlags",
          "examples": [
            {
              "id": "basic_setGroupPropertiesForFlags",
              "name": "Basic setGroupPropertiesForFlags",
              "code": "PostHogSDK.shared.setGroupPropertiesForFlags(\"__value\", properties: \"properties_value\")"
            }
          ],
          "releaseTag": "public",
          "params": [
            {
              "name": "_",
              "type": "String",
              "isOptional": false
            },
            {
              "name": "properties",
              "type": "String",
              "isOptional": false
            }
          ],
          "returnType": {
            "id": "Void",
            "name": "Void"
          },
          "path": "PostHog/PostHogSDK.swift"
        },
        {
          "category": "Feature flags",
          "description": "Sets properties for a specific group type to include when evaluating feature flags.   These properties supplement the standard group information sent to PostHog for flag evaluation,   providing additional context that can be used in flag targeting conditions.",
          "details": "Sets properties for a specific group type to include when evaluating feature flags.   These properties supplement the standard group information sent to PostHog for flag evaluation,   providing additional context that can be used in flag targeting conditions.",
          "id": "setGroupPropertiesForFlags",
          "showDocs": true,
          "title": "setGroupPropertiesForFlags",
          "examples": [
            {
              "id": "basic_setGroupPropertiesForFlags",
              "name": "Basic setGroupPropertiesForFlags",
              "code": "PostHogSDK.shared.setGroupPropertiesForFlags(\"__value\", properties: \"properties_value\", reloadFeatureFlags: true)"
            }
          ],
          "releaseTag": "public",
          "params": [
            {
              "name": "_",
              "type": "String",
              "isOptional": false
            },
            {
              "name": "properties",
              "type": "String",
              "isOptional": false
            },
            {
              "name": "reloadFeatureFlags",
              "type": "Bool",
              "isOptional": false
            }
          ],
          "returnType": {
            "id": "Void",
            "name": "Void"
          },
          "path": "PostHog/PostHogSDK.swift"
        },
        {
          "category": "Feature flags",
          "description": "Sets person properties that will be included in feature flag evaluation requests.",
          "details": "Sets person properties that will be included in feature flag evaluation requests.",
          "id": "setPersonPropertiesForFlags",
          "showDocs": true,
          "title": "setPersonPropertiesForFlags",
          "examples": [
            {
              "id": "basic_setPersonPropertiesForFlags",
              "name": "Basic setPersonPropertiesForFlags",
              "code": "PostHogSDK.shared.setPersonPropertiesForFlags()"
            }
          ],
          "releaseTag": "public",
          "params": [],
          "returnType": {
            "id": "Void",
            "name": "Void"
          },
          "path": "PostHog/PostHogSDK.swift"
        },
        {
          "category": "Feature flags",
          "description": "Sets person properties that will be included in feature flag evaluation requests.",
          "details": "Sets person properties that will be included in feature flag evaluation requests.",
          "id": "setPersonPropertiesForFlags",
          "showDocs": true,
          "title": "setPersonPropertiesForFlags",
          "examples": [
            {
              "id": "basic_setPersonPropertiesForFlags",
              "name": "Basic setPersonPropertiesForFlags",
              "code": "PostHogSDK.shared.setPersonPropertiesForFlags()"
            }
          ],
          "releaseTag": "public",
          "params": [],
          "returnType": {
            "id": "Void",
            "name": "Void"
          },
          "path": "PostHog/PostHogSDK.swift"
        },
        {
          "category": "Initialization",
          "description": "setup method",
          "details": "Detailed description of setup",
          "id": "setup",
          "showDocs": true,
          "title": "setup",
          "examples": [
            {
              "id": "basic_setup",
              "name": "Basic setup",
              "code": "PostHogSDK.shared.setup(value)"
            }
          ],
          "releaseTag": "public",
          "params": [
            {
              "name": "value",
              "type": "PostHogConfig",
              "isOptional": false
            }
          ],
          "returnType": {
            "id": "Void",
            "name": "Void"
          },
          "path": "PostHog/PostHogSDK.swift"
        },
        {
          "category": "Session replay",
          "description": "startSession method",
          "details": "Detailed description of startSession",
          "id": "startSession",
          "showDocs": true,
          "title": "startSession",
          "examples": [
            {
              "id": "basic_startSession",
              "name": "Basic startSession",
              "code": "PostHogSDK.shared.startSession()"
            }
          ],
          "releaseTag": "public",
          "params": [],
          "returnType": {
            "id": "Void",
            "name": "Void"
          },
          "path": "PostHog/PostHogSDK.swift"
        },
        {
          "category": "Configuration",
          "description": "unregister method",
          "details": "Detailed description of unregister",
          "id": "unregister",
          "showDocs": true,
          "title": "unregister",
          "examples": [
            {
              "id": "basic_unregister",
              "name": "Basic unregister",
              "code": "PostHogSDK.shared.unregister(\"value_value\")"
            }
          ],
          "releaseTag": "public",
          "params": [
            {
              "name": "value",
              "type": "String",
              "isOptional": false
            }
          ],
          "returnType": {
            "id": "Void",
            "name": "Void"
          },
          "path": "PostHog/PostHogSDK.swift"
        },
        {
          "category": "Initialization",
          "description": "with method",
          "details": "Detailed description of with",
          "id": "with",
          "showDocs": true,
          "title": "with",
          "examples": [
            {
              "id": "basic_with",
              "name": "Basic with",
              "code": "PostHogSDK.shared.with(value, value: value)"
            }
          ],
          "releaseTag": "public",
          "params": [
            {
              "name": "value",
              "type": "PostHogConfig",
              "isOptional": false
            },
            {
              "name": "value",
              "type": "PostHogSDK",
              "isOptional": false
            }
          ],
          "returnType": {
            "id": "Void",
            "name": "Void"
          },
          "path": "PostHog/PostHogSDK.swift"
        }
      ]
    },
    {
      "description": "A model representing a PostHog survey to be displayed to users",
      "id": "PostHogDisplaySurvey",
      "title": "PostHogDisplaySurvey",
      "functions": []
    },
    {
      "description": "Represents a question with a clickable link",
      "id": "PostHogDisplayLinkQuestion",
      "title": "PostHogDisplayLinkQuestion",
      "functions": []
    },
    {
      "description": "Represents a multiple or single choice question where users can select one or more options",
      "id": "PostHogDisplayChoiceQuestion",
      "title": "PostHogDisplayChoiceQuestion",
      "functions": []
    },
    {
      "description": "A model representing the next state of the survey progression.",
      "id": "PostHogNextSurveyQuestion",
      "title": "PostHogNextSurveyQuestion",
      "functions": []
    },
    {
      "description": "The PostHogStorageManager class",
      "id": "PostHogStorageManager",
      "title": "PostHogStorageManager",
      "functions": [
        {
          "category": "Identification",
          "description": "getAnonymousId method",
          "details": "Detailed description of getAnonymousId",
          "id": "getAnonymousId",
          "showDocs": true,
          "title": "getAnonymousId",
          "examples": [
            {
              "id": "basic_getAnonymousId",
              "name": "Basic getAnonymousId",
              "code": "PostHogStorageManager.shared.getAnonymousId()"
            }
          ],
          "releaseTag": "public",
          "params": [],
          "returnType": {
            "id": "Void",
            "name": "Void"
          },
          "path": "PostHog/PostHogStorageManager.swift"
        },
        {
          "category": "Identification",
          "description": "getDistinctId method",
          "details": "Detailed description of getDistinctId",
          "id": "getDistinctId",
          "showDocs": true,
          "title": "getDistinctId",
          "examples": [
            {
              "id": "basic_getDistinctId",
              "name": "Basic getDistinctId",
              "code": "PostHogStorageManager.shared.getDistinctId()"
            }
          ],
          "releaseTag": "public",
          "params": [],
          "returnType": {
            "id": "Void",
            "name": "Void"
          },
          "path": "PostHog/PostHogStorageManager.swift"
        },
        {
          "category": "Configuration",
          "description": "isIdentified method",
          "details": "Detailed description of isIdentified",
          "id": "isIdentified",
          "showDocs": true,
          "title": "isIdentified",
          "examples": [
            {
              "id": "basic_isIdentified",
              "name": "Basic isIdentified",
              "code": "PostHogStorageManager.shared.isIdentified()"
            }
          ],
          "releaseTag": "public",
          "params": [],
          "returnType": {
            "id": "Void",
            "name": "Void"
          },
          "path": "PostHog/PostHogStorageManager.swift"
        },
        {
          "category": "Configuration",
          "description": "isPersonProcessing method",
          "details": "Detailed description of isPersonProcessing",
          "id": "isPersonProcessing",
          "showDocs": true,
          "title": "isPersonProcessing",
          "examples": [
            {
              "id": "basic_isPersonProcessing",
              "name": "Basic isPersonProcessing",
              "code": "PostHogStorageManager.shared.isPersonProcessing()"
            }
          ],
          "releaseTag": "public",
          "params": [],
          "returnType": {
            "id": "Void",
            "name": "Void"
          },
          "path": "PostHog/PostHogStorageManager.swift"
        },
        {
          "category": "Privacy",
          "description": "reset method",
          "details": "Detailed description of reset",
          "id": "reset",
          "showDocs": true,
          "title": "reset",
          "examples": [
            {
              "id": "basic_reset",
              "name": "Basic reset",
              "code": "PostHogStorageManager.shared.reset(true, _: true)"
            }
          ],
          "releaseTag": "public",
          "params": [
            {
              "name": "keepAnonymousId",
              "type": "Bool",
              "isOptional": false
            },
            {
              "name": "_",
              "type": "Bool",
              "isOptional": false
            }
          ],
          "returnType": {
            "id": "Void",
            "name": "Void"
          },
          "path": "PostHog/PostHogStorageManager.swift"
        },
        {
          "category": "Configuration",
          "description": "setAnonymousId method",
          "details": "Detailed description of setAnonymousId",
          "id": "setAnonymousId",
          "showDocs": true,
          "title": "setAnonymousId",
          "examples": [
            {
              "id": "basic_setAnonymousId",
              "name": "Basic setAnonymousId",
              "code": "PostHogStorageManager.shared.setAnonymousId(\"value_value\")"
            }
          ],
          "releaseTag": "public",
          "params": [
            {
              "name": "value",
              "type": "String",
              "isOptional": false
            }
          ],
          "returnType": {
            "id": "Void",
            "name": "Void"
          },
          "path": "PostHog/PostHogStorageManager.swift"
        },
        {
          "category": "Configuration",
          "description": "setDistinctId method",
          "details": "Detailed description of setDistinctId",
          "id": "setDistinctId",
          "showDocs": true,
          "title": "setDistinctId",
          "examples": [
            {
              "id": "basic_setDistinctId",
              "name": "Basic setDistinctId",
              "code": "PostHogStorageManager.shared.setDistinctId(\"value_value\")"
            }
          ],
          "releaseTag": "public",
          "params": [
            {
              "name": "value",
              "type": "String",
              "isOptional": false
            }
          ],
          "returnType": {
            "id": "Void",
            "name": "Void"
          },
          "path": "PostHog/PostHogStorageManager.swift"
        },
        {
          "category": "Configuration",
          "description": "setIdentified method",
          "details": "Detailed description of setIdentified",
          "id": "setIdentified",
          "showDocs": true,
          "title": "setIdentified",
          "examples": [
            {
              "id": "basic_setIdentified",
              "name": "Basic setIdentified",
              "code": "PostHogStorageManager.shared.setIdentified(true)"
            }
          ],
          "releaseTag": "public",
          "params": [
            {
              "name": "value",
              "type": "Bool",
              "isOptional": false
            }
          ],
          "returnType": {
            "id": "Void",
            "name": "Void"
          },
          "path": "PostHog/PostHogStorageManager.swift"
        },
        {
          "category": "Configuration",
          "description": "setPersonProcessing method",
          "details": "Detailed description of setPersonProcessing",
          "id": "setPersonProcessing",
          "showDocs": true,
          "title": "setPersonProcessing",
          "examples": [
            {
              "id": "basic_setPersonProcessing",
              "name": "Basic setPersonProcessing",
              "code": "PostHogStorageManager.shared.setPersonProcessing(true)"
            }
          ],
          "releaseTag": "public",
          "params": [
            {
              "name": "value",
              "type": "Bool",
              "isOptional": false
            }
          ],
          "returnType": {
            "id": "Void",
            "name": "Void"
          },
          "path": "PostHog/PostHogStorageManager.swift"
        }
      ]
    },
    {
      "description": "Represents an open-ended question where users can input free-form text",
      "id": "PostHogDisplayOpenQuestion",
      "title": "PostHogDisplayOpenQuestion",
      "functions": []
    },
    {
      "description": "The PostHogEvent class",
      "id": "PostHogEvent",
      "title": "PostHogEvent",
      "functions": []
    },
    {
      "description": "The PostHogConfig class",
      "id": "PostHogConfig",
      "title": "PostHogConfig",
      "functions": [
        {
          "category": "Configuration",
          "description": "setBeforeSend method",
          "details": "Detailed description of setBeforeSend",
          "id": "setBeforeSend",
          "showDocs": true,
          "title": "setBeforeSend",
          "examples": [
            {
              "id": "basic_setBeforeSend",
              "name": "Basic setBeforeSend",
              "code": "PostHogConfig.shared.setBeforeSend(value)"
            }
          ],
          "releaseTag": "public",
          "params": [
            {
              "name": "value",
              "type": "BeforeSendBlock",
              "isOptional": false
            }
          ],
          "returnType": {
            "id": "Void",
            "name": "Void"
          },
          "path": "PostHog/PostHogConfig.swift"
        },
        {
          "category": "Configuration",
          "description": "setBeforeSend method",
          "details": "Detailed description of setBeforeSend",
          "id": "setBeforeSend",
          "showDocs": true,
          "title": "setBeforeSend",
          "examples": [
            {
              "id": "basic_setBeforeSend",
              "name": "Basic setBeforeSend",
              "code": "PostHogConfig.shared.setBeforeSend()"
            }
          ],
          "releaseTag": "public",
          "params": [],
          "returnType": {
            "id": "Void",
            "name": "Void"
          },
          "path": "PostHog/PostHogConfig.swift"
        }
      ]
    },
    {
      "description": "A model representing a user\u2019s response to a survey question",
      "id": "PostHogSurveyResponse",
      "title": "PostHogSurveyResponse",
      "functions": [
        {
          "category": "Configuration",
          "description": "Creates a response for a link question",
          "details": "Creates a response for a link question",
          "id": "link",
          "showDocs": true,
          "title": "link",
          "examples": [
            {
              "id": "basic_link",
              "name": "Basic link",
              "code": "PostHogSurveyResponse.shared.link(true, value: value)"
            }
          ],
          "releaseTag": "public",
          "params": [
            {
              "name": "value",
              "type": "Bool",
              "isOptional": false
            },
            {
              "name": "value",
              "type": "PostHogSurveyResponse",
              "isOptional": false
            }
          ],
          "returnType": {
            "id": "Void",
            "name": "Void"
          },
          "path": "PostHog/PostHogSurveyResponse.swift"
        },
        {
          "category": "Configuration",
          "description": "Creates a response for a multiple-choice question",
          "details": "Creates a response for a multiple-choice question",
          "id": "multipleChoice",
          "showDocs": true,
          "title": "multipleChoice",
          "examples": [
            {
              "id": "basic_multipleChoice",
              "name": "Basic multipleChoice",
              "code": "PostHogSurveyResponse.shared.multipleChoice()"
            }
          ],
          "releaseTag": "public",
          "params": [],
          "returnType": {
            "id": "Void",
            "name": "Void"
          },
          "path": "PostHog/PostHogSurveyResponse.swift"
        },
        {
          "category": "Configuration",
          "description": "Creates a response for an open-ended question",
          "details": "Creates a response for an open-ended question",
          "id": "openEnded",
          "showDocs": true,
          "title": "openEnded",
          "examples": [
            {
              "id": "basic_openEnded",
              "name": "Basic openEnded",
              "code": "PostHogSurveyResponse.shared.openEnded(\"value_value\", value: value)"
            }
          ],
          "releaseTag": "public",
          "params": [
            {
              "name": "value",
              "type": "String",
              "isOptional": false
            },
            {
              "name": "value",
              "type": "PostHogSurveyResponse",
              "isOptional": false
            }
          ],
          "returnType": {
            "id": "Void",
            "name": "Void"
          },
          "path": "PostHog/PostHogSurveyResponse.swift"
        },
        {
          "category": "Configuration",
          "description": "Creates a response for a rating question",
          "details": "Creates a response for a rating question",
          "id": "rating",
          "showDocs": true,
          "title": "rating",
          "examples": [
            {
              "id": "basic_rating",
              "name": "Basic rating",
              "code": "PostHogSurveyResponse.shared.rating(value, value: value)"
            }
          ],
          "releaseTag": "public",
          "params": [
            {
              "name": "value",
              "type": "Int",
              "isOptional": false
            },
            {
              "name": "value",
              "type": "PostHogSurveyResponse",
              "isOptional": false
            }
          ],
          "returnType": {
            "id": "Void",
            "name": "Void"
          },
          "path": "PostHog/PostHogSurveyResponse.swift"
        },
        {
          "category": "Configuration",
          "description": "Creates a response for a single-choice question",
          "details": "Creates a response for a single-choice question",
          "id": "singleChoice",
          "showDocs": true,
          "title": "singleChoice",
          "examples": [
            {
              "id": "basic_singleChoice",
              "name": "Basic singleChoice",
              "code": "PostHogSurveyResponse.shared.singleChoice(\"value_value\", value: value)"
            }
          ],
          "releaseTag": "public",
          "params": [
            {
              "name": "value",
              "type": "String",
              "isOptional": false
            },
            {
              "name": "value",
              "type": "PostHogSurveyResponse",
              "isOptional": false
            }
          ],
          "returnType": {
            "id": "Void",
            "name": "Void"
          },
          "path": "PostHog/PostHogSurveyResponse.swift"
        }
      ]
    },
    {
      "description": "Base class for all survey question types",
      "id": "PostHogDisplaySurveyQuestion",
      "title": "PostHogDisplaySurveyQuestion",
      "functions": []
    },
    {
      "description": "The PostHogSessionManager class",
      "id": "PostHogSessionManager",
      "title": "PostHogSessionManager",
      "functions": [
        {
          "category": "Session replay",
          "description": "setSessionId method",
          "details": "Detailed description of setSessionId",
          "id": "setSessionId",
          "showDocs": true,
          "title": "setSessionId",
          "examples": [
            {
              "id": "basic_setSessionId",
              "name": "Basic setSessionId",
              "code": "PostHogSessionManager.shared.setSessionId(\"value_value\")"
            }
          ],
          "releaseTag": "public",
          "params": [
            {
              "name": "value",
              "type": "String",
              "isOptional": false
            }
          ],
          "returnType": {
            "id": "Void",
            "name": "Void"
          },
          "path": "PostHog/PostHogSessionManager.swift"
        }
      ]
    },
    {
      "description": "The PostHogSurveysConfig class",
      "id": "PostHogSurveysConfig",
      "title": "PostHogSurveysConfig",
      "functions": []
    },
    {
      "description": "Represents a rating question where users can select a rating from a scale",
      "id": "PostHogDisplayRatingQuestion",
      "title": "PostHogDisplayRatingQuestion",
      "functions": []
    },
    {
      "description": "Model that describes the appearance customization of a PostHog survey",
      "id": "PostHogDisplaySurveyAppearance",
      "title": "PostHogDisplaySurveyAppearance",
      "functions": []
    }
  ],
  "types": [
    {
      "id": "PostHogSurveyResponseType",
      "name": "PostHogSurveyResponseType",
      "description": "PostHogSurveyResponseType type",
      "properties": [],
      "path": "PostHog/PostHogSurveyResponseType.swift",
      "example": "PostHogSurveyResponseType()"
    },
    {
      "id": "PostHogDisplaySurveyTextContentType",
      "name": "PostHogDisplaySurveyTextContentType",
      "description": "Content type for text-based survey elements",
      "properties": [],
      "path": "PostHog/PostHogDisplaySurveyTextContentType.swift",
      "example": "PostHogDisplaySurveyTextContentType()"
    },
    {
      "id": "PostHogDisplaySurveyRatingType",
      "name": "PostHogDisplaySurveyRatingType",
      "description": "Type of rating display for survey rating questions",
      "properties": [],
      "path": "PostHog/PostHogDisplaySurveyRatingType.swift",
      "example": "PostHogDisplaySurveyRatingType()"
    },
    {
      "id": "PostHogPersonProfiles",
      "name": "PostHogPersonProfiles",
      "description": "Determines the behavior for processing user profiles.",
      "properties": [],
      "path": "PostHog/PostHogPersonProfiles.swift",
      "example": "PostHogPersonProfiles()"
    },
    {
      "id": "PostHogConfig.PostHogDataMode",
      "name": "PostHogConfig.PostHogDataMode",
      "description": "PostHogConfig.PostHogDataMode type",
      "properties": [],
      "path": "PostHog/PostHogConfig.PostHogDataMode.swift",
      "example": "PostHogConfig.PostHogDataMode()"
    }
  ],
  "categories": [
    "Initialization",
    "Identification",
    "Capture",
    "Feature flags",
    "Session replay",
    "Privacy",
    "Configuration"
  ]
}